contextmaker/__init__.py
contextmaker/contextmaker.py
contextmaker/converters/__init__.py
contextmaker/converters/nonsphinx_converter.py
contextmaker/converters/notebook_converter.py
contextmaker/converters/raw_source_code_converter.py
contextmaker/converters/sphinx_build_converter.py
contextmaker/converters/sphinx_makefile_converter.py
contextmaker/converters/utils/__init__.py
contextmaker/converters/utils/detector.py
contextmaker/converters/utils/markdown_builder.py
contextmaker/converters/utils/notebook_utils.py
contextmaker/converters/utils/text_converter.py
contextmaker/utils/__init__.py
contextmaker/utils/dependency_installer.py
contextmaker-1.8.8.dist-info/licenses/LICENSE
contextmaker-1.8.8.dist-info/METADATA
contextmaker-1.8.8.dist-info/WHEEL
contextmaker-1.8.8.dist-info/entry_points.txt
contextmaker-1.8.8.dist-info/top_level.txt
contextmaker-1.8.8.dist-info/RECORD
