Metadata-Version: 2.4
Name: contextmaker
Version: 1.8.8
Summary: A simple context builder and converter toolkit
Author-email: Chadi Ait Ekioui <chadiaitek2004@gmail.com>
License: MIT
Project-URL: Homepage, https://github.com/chadiaitekioui/contextmaker
Project-URL: Repository, https://github.com/chadiaitekioui/contextmaker
Requires-Python: >=3.8
License-File: LICENSE
Requires-Dist: sphinx>=5.0.0
Requires-Dist: jupytext>=1.14.0
Requires-Dist: sphinx-rtd-theme>=1.0.0
Requires-Dist: myst-parser>=1.0.0
Requires-Dist: sphinx-markdown-builder>=0.6.5
Requires-Dist: markdownify
Requires-Dist: rich
Requires-Dist: beautifulsoup4
Requires-Dist: html2text
Requires-Dist: markdown
Requires-Dist: numpy
Requires-Dist: docutils
Requires-Dist: jinja2
Requires-Dist: pygments
Requires-Dist: nbformat
Requires-Dist: nbconvert
Requires-Dist: jupyter
Provides-Extra: dev
Requires-Dist: pytest; extra == "dev"
Requires-Dist: black; extra == "dev"
Requires-Dist: sphinx-autobuild; extra == "dev"
Dynamic: license-file
